mindfactory/__init__.py
mindfactory/items.py
mindfactory/middlewares.py
mindfactory/settings.py
mindfactory/pipelines/__init__.py
mindfactory/pipelines/database_pipeline.py
mindfactory/pipelines/duplicates_pipeline.py
mindfactory/pipelines/rating_pipeline.py
mindfactory/spiders/__init__.py
mindfactory/spiders/product_spider.py
mindfactory_crawling-1.0.4.dist-info/LICENSE
mindfactory_crawling-1.0.4.dist-info/METADATA
mindfactory_crawling-1.0.4.dist-info/WHEEL
mindfactory_crawling-1.0.4.dist-info/entry_points.txt
mindfactory_crawling-1.0.4.dist-info/top_level.txt
mindfactory_crawling-1.0.4.dist-info/RECORD
