Metadata-Version: 2.1
Name: mindfactory-crawling
Version: 1.0.4
Summary: A crawler for mindfactory.de
Home-page: https://github.com/RobMcH/mindfactory_crawling
Author: Robert McHardy
Author-email: robert@robertmchardy.de
License: UNKNOWN
Platform: UNKNOWN
Classifier: Programming Language :: Python :: 3
Classifier: Programming Language :: Python :: 3.5
Classifier: Programming Language :: Python :: 3.6
Classifier: Programming Language :: Python :: 3.7
Classifier: Programming Language :: Python :: 3.8
Classifier: License :: OSI Approved :: MIT License
Classifier: Operating System :: OS Independent
Requires-Dist: scrapy
